gh_release-0.1.2.data/scripts/ghrelease
gh_release-0.1.2.dist-info/DESCRIPTION.rst
gh_release-0.1.2.dist-info/METADATA
gh_release-0.1.2.dist-info/RECORD
gh_release-0.1.2.dist-info/WHEEL
gh_release-0.1.2.dist-info/metadata.json
gh_release-0.1.2.dist-info/top_level.txt
ghrelease/__init__.py
ghrelease/cli.py
ghrelease/upload_gh.py
